druzhba/__init__.py
druzhba/_version.py
druzhba/avro.py
druzhba/config.py
druzhba/db.py
druzhba/main.py
druzhba/monitoring.py
druzhba/mssql.py
druzhba/mysql.py
druzhba/postgres.py
druzhba/redshift.py
druzhba/table.py
druzhba-0.2.1.dist-info/LICENSE
druzhba-0.2.1.dist-info/METADATA
druzhba-0.2.1.dist-info/WHEEL
druzhba-0.2.1.dist-info/entry_points.txt
druzhba-0.2.1.dist-info/top_level.txt
druzhba-0.2.1.dist-info/RECORD
