Metadata-Version: 2.1
Name: druzhba
Version: 0.2.1
Summary: A friendly data pipeline framework
Home-page: https://github.com/seatgeek/druzhba
Author: Seatgeek and Contributors
Author-email: druzhba-maintainers@seatgeek.com
License: MIT License
Platform: UNKNOWN
Classifier: Programming Language :: Python :: 3
Classifier: License :: OSI Approved :: MIT License
Classifier: Operating System :: OS Independent
Requires-Python: >=3.6
Requires-Dist: boto3 (>=1.10.34)
Requires-Dist: botocore (>=1.13.35)
Requires-Dist: fastavro (<0.22,>=0.21.22)
Requires-Dist: Jinja2 (>=2.10)
Requires-Dist: psycopg2-binary (>=2.7.3.2)
Requires-Dist: pyaml (>=17.10.0)
Requires-Dist: pymssql (<3.0)
Requires-Dist: pymysql (<0.10,>=0.7.11)
Requires-Dist: sentry-sdk (<0.14,>=0.11.0)
Requires-Dist: statsd (>=3.3.0)
Provides-Extra: dev
Requires-Dist: autoflake ; extra == 'dev'
Requires-Dist: black ; extra == 'dev'
Requires-Dist: isort ; extra == 'dev'
Requires-Dist: sphinx ; extra == 'dev'
Requires-Dist: recommonmark ; extra == 'dev'
Requires-Dist: twine ; extra == 'dev'
Provides-Extra: test
Requires-Dist: nose (>=1.3.7) ; extra == 'test'
Requires-Dist: mock (>=2.0.0) ; extra == 'test'
Requires-Dist: pylint (==2.5.3) ; extra == 'test'
